Metadata-Version: 2.1
Name: zpool-status
Version: 0.2.3
Summary: Parse output from zpool status
Home-page: https://github.com/gustaebel/zpool-status/
Author: Lars Gustäbel
Author-email: lars@gustaebel.de
License: BSD
Classifier: Development Status :: 3 - Alpha
Classifier: Environment :: Console
Classifier: Intended Audience :: Developers
Classifier: Intended Audience :: System Administrators
Classifier: License :: OSI Approved :: BSD License
Classifier: Operating System :: POSIX
Classifier: Operating System :: POSIX :: Linux
Classifier: Topic :: File Formats :: JSON
Classifier: Topic :: Software Development :: Libraries :: Python Modules
Classifier: Topic :: System :: Filesystems
Classifier: Topic :: Utilities
Classifier: Programming Language :: Python :: 3
Requires-Python: >=3.7
License-File: LICENSE
